pyaibot/__init__.py
pyaibot-0.0.2.dist-info/METADATA
pyaibot-0.0.2.dist-info/WHEEL
pyaibot-0.0.2.dist-info/entry_points.txt
pyaibot-0.0.2.dist-info/top_level.txt
pyaibot-0.0.2.dist-info/RECORD
