Metadata-Version: 2.2
Name: pyaibot
Version: 0.0.2
Summary: AI百宝箱
Author: jiaosenvip
Author-email: jiaosenvip <jiaosenvip@163.com>
License: MIT
Project-URL: HomePage, https://github.com/jiaosenvip/pyaibot
Keywords: ai,aibot,gpt
Requires-Python: >=3.10
Requires-Dist: pywebview
